Metadata-Version: 2.1
Name: latex-code-create
Version: 1.0
Summary: LaTeX code generation for creating tables and adding images
Author: Ekaterina Shapochnik
